data3/__init__.py
data3/columnObject.py
data3/databaseObject.py
data3/rowObject.py
data3/searchParams.py
data3/tableObject.py
data3-1.0.1.dist-info/LICENSE
data3-1.0.1.dist-info/METADATA
data3-1.0.1.dist-info/WHEEL
data3-1.0.1.dist-info/top_level.txt
data3-1.0.1.dist-info/RECORD
