Metadata-Version: 2.1
Name: data3
Version: 1.0.1
Summary: SQLite3 Wrapper for Python
Home-page: https://github.com/jamescalam/aesthetic_ascii
Author: Kieran van der Heijde
Author-email: kieran.van.der.heijde@gmail.com
Classifier: Programming Language :: Python :: 3
Classifier: License :: OSI Approved :: MIT License
Classifier: Operating System :: OS Independent
Requires-Python: >=3.7
License-File: LICENSE
